get4u/__init__.py
get4u-0.0.0.dist-info/METADATA
get4u-0.0.0.dist-info/WHEEL
get4u-0.0.0.dist-info/top_level.txt
get4u-0.0.0.dist-info/RECORD
