Metadata-Version: 2.4
Name: get4u
Version: 0.0.0
Author-email: Dominik Müller <mulldo53@gmail.com>
Project-URL: homepage, https://gitlab.com/loroka/get4u
Project-URL: documentation, https://gitlab.com/loroka/get4u
Project-URL: repository, https://gitlab.com/loroka/mget4u
Requires-Python: >=3.6
Provides-Extra: test
Requires-Dist: pytest; extra == "test"
Provides-Extra: dev
Requires-Dist: mypy; extra == "dev"
Requires-Dist: yapf; extra == "dev"
